hotel_manage_me/__init__.py
hotel_manage_me/booking.py
hotel_manage-0.0.1.dist-info/LICENSE
hotel_manage-0.0.1.dist-info/METADATA
hotel_manage-0.0.1.dist-info/WHEEL
hotel_manage-0.0.1.dist-info/top_level.txt
hotel_manage-0.0.1.dist-info/RECORD
