Metadata-Version: 2.1
Name: hotel-manage
Version: 0.0.1
Summary: Testing Hotel Manage Library
Author-email: Muhammad Ahmad <heremuhammadahmad@gmail.com>
Project-URL: Homepage, https://github.com/iammuhammadahmad
Project-URL: Bug Tracker, https://github.com/iammuhammadahmad
Classifier: Programming Language :: Python :: 3
Classifier: License :: OSI Approved :: MIT License
Classifier: Operating System :: OS Independent
Requires-Python: >=3.7
License-File: LICENSE
